tkg_utils/AppletAdapter.py
tkg_utils/SdkAdapter.py
tkg_utils/__init__.py
tkg_utils/Normal/ItemInfo.py
tkg_utils/Normal/__init__.py
tkg_utils/SdkAdapter/FileAdapter.py
tkg_utils/SdkAdapter/FileContentAdapter.py
tkg_utils/SdkAdapter/FileItem.py
tkg_utils/SdkAdapter/SdkAdapter.py
tkg_utils/SdkAdapter/__init__.py
tkg_utils/Utils/FileUtils.py
tkg_utils/Utils/PrettyFile.py
tkg_utils/Utils/__init__.py
tkg_utils-2.0.3.dist-info/LICENSE
tkg_utils-2.0.3.dist-info/METADATA
tkg_utils-2.0.3.dist-info/WHEEL
tkg_utils-2.0.3.dist-info/top_level.txt
tkg_utils-2.0.3.dist-info/RECORD
