Metadata-Version: 2.2
Name: tkg_utils
Version: 2.0.3
Summary: tkg_utils
Home-page: https://github.com/BigDataFounder/tkg_utils
Author: gengch
Author-email: gengchuanhua@163.com
License: MIT
License-File: LICENSE
Dynamic: author
Dynamic: author-email
Dynamic: home-page
Dynamic: license
Dynamic: summary
